mcp_kafka/__init__.py
mcp_kafka/__main__.py
mcp_kafka/config.py
mcp_kafka/version.py
mcp_kafka/auth/__init__.py
mcp_kafka/auth/middleware.py
mcp_kafka/fastmcp_tools/__init__.py
mcp_kafka/fastmcp_tools/cluster.py
mcp_kafka/fastmcp_tools/common.py
mcp_kafka/fastmcp_tools/consumer_group.py
mcp_kafka/fastmcp_tools/message.py
mcp_kafka/fastmcp_tools/registration.py
mcp_kafka/fastmcp_tools/topic.py
mcp_kafka/kafka_wrapper/__init__.py
mcp_kafka/kafka_wrapper/client.py
mcp_kafka/middleware/__init__.py
mcp_kafka/middleware/audit.py
mcp_kafka/middleware/debug_logging.py
mcp_kafka/middleware/rate_limit.py
mcp_kafka/middleware/safety.py
mcp_kafka/middleware/stack.py
mcp_kafka/middleware/utils.py
mcp_kafka/safety/__init__.py
mcp_kafka/safety/core.py
mcp_kafka/utils/__init__.py
mcp_kafka/utils/errors.py
mcp_kafka/utils/logger.py
mcp_kafka-0.1.0.dist-info/METADATA
mcp_kafka-0.1.0.dist-info/WHEEL
mcp_kafka-0.1.0.dist-info/entry_points.txt
mcp_kafka-0.1.0.dist-info/licenses/LICENSE
mcp_kafka-0.1.0.dist-info/RECORD
