Metadata-Version: 2.4
Name: mcp-kafka
Version: 0.1.0
Summary: Model Context Protocol server for Apache Kafka
Project-URL: Homepage, https://github.com/williajm/mcp_kafka
Project-URL: Repository, https://github.com/williajm/mcp_kafka
Project-URL: Issues, https://github.com/williajm/mcp_kafka/issues
Project-URL: Changelog, https://github.com/williajm/mcp_kafka/releases
Project-URL: PyPI, https://pypi.org/project/mcp-kafka/
Author: James Williams
License: MIT
License-File: LICENSE
Keywords: ai,apache-kafka,claude,kafka,llm,mcp,model-context-protocol,streaming
Classifier: Development Status :: 3 - Alpha
Classifier: Intended Audience :: Developers
Classifier: Intended Audience :: System Administrators
Classifier: License :: OSI Approved :: MIT License
Classifier: Operating System :: OS Independent
Classifier: Programming Language :: Python :: 3
Classifier: Programming Language :: Python :: 3.11
Classifier: Programming Language :: Python :: 3.12
Classifier: Programming Language :: Python :: 3.13
Classifier: Programming Language :: Python :: 3.14
Classifier: Topic :: Software Development :: Libraries :: Python Modules
Classifier: Topic :: System :: Systems Administration
Classifier: Topic :: Utilities
Classifier: Typing :: Typed
Requires-Python: >=3.11
Requires-Dist: authlib>=1.6.6
Requires-Dist: confluent-kafka>=2.3.0
Requires-Dist: fastmcp>=2.14.3
Requires-Dist: httpx>=0.28.1
Requires-Dist: limits>=5.6.0
Requires-Dist: loguru>=0.7.3
Requires-Dist: pydantic-settings>=2.12.0
Requires-Dist: pydantic>=2.12.5
Requires-Dist: starlette>=0.50.0
Requires-Dist: typer>=0.20.0
Requires-Dist: uvicorn>=0.38.0
Provides-Extra: dev
Requires-Dist: hypothesis>=6.148.7; extra == 'dev'
Requires-Dist: mypy>=1.19.1; extra == 'dev'
Requires-Dist: pytest-asyncio>=1.3.0; extra == 'dev'
Requires-Dist: pytest-cov>=7.0.0; extra == 'dev'
Requires-Dist: pytest>=9.0.2; extra == 'dev'
Requires-Dist: ruff>=0.14.9; extra == 'dev'
Requires-Dist: testcontainers>=4.0.0; extra == 'dev'
Provides-Extra: fuzz
Requires-Dist: atheris>=3.0.0; extra == 'fuzz'
